bs4_utils/__init__.py
bs4_utils/__init__.pyi
bs4_utils/py.typed
bs4_utils-0.3.0.dist-info/LICENSE
bs4_utils-0.3.0.dist-info/METADATA
bs4_utils-0.3.0.dist-info/WHEEL
bs4_utils-0.3.0.dist-info/RECORD
