Metadata-Version: 2.1
Name: bs4-utils
Version: 0.3.0
Summary: A BeautifulSoup wrapper with helpful utils.
License: MIT
Author: J.I. Cruz
Author-email: hello@jicruz.com
Requires-Python: >=3.11,<4.0
Classifier: License :: OSI Approved :: MIT License
Classifier: Programming Language :: Python :: 3
Classifier: Programming Language :: Python :: 3.11
Classifier: Programming Language :: Python :: 3.12
Requires-Dist: beautifulsoup4
